jnt_django_toolbox/__init__.py
jnt_django_toolbox/admin/__init__.py
jnt_django_toolbox/admin/content_type.py
jnt_django_toolbox/admin/fields/__init__.py
jnt_django_toolbox/admin/fields/changelist.py
jnt_django_toolbox/admin/filters/__init__.py
jnt_django_toolbox/admin/filters/autocomplete.py
jnt_django_toolbox/admin/forms/__init__.py
jnt_django_toolbox/admin/forms/widgets/__init__.py
jnt_django_toolbox/admin/forms/widgets/readonly/__init__.py
jnt_django_toolbox/admin/forms/widgets/readonly/base.py
jnt_django_toolbox/admin/forms/widgets/readonly/boolean.py
jnt_django_toolbox/admin/forms/widgets/readonly/foreign_key.py
jnt_django_toolbox/admin/forms/widgets/readonly/generic_foreign_key.py
jnt_django_toolbox/admin/forms/widgets/readonly/many_to_many.py
jnt_django_toolbox/admin/forms/widgets/readonly/permissions_readonly.py
jnt_django_toolbox/admin/forms/widgets/readonly/string_field.py
jnt_django_toolbox/admin/helpers/__init__.py
jnt_django_toolbox/admin/helpers/urls.py
jnt_django_toolbox/admin/helpers/widgets.py
jnt_django_toolbox/admin/mixins/__init__.py
jnt_django_toolbox/admin/mixins/autocomplete.py
jnt_django_toolbox/admin/mixins/autocomplete_changelist_filters.py
jnt_django_toolbox/admin/mixins/autocomplete_fields.py
jnt_django_toolbox/admin/mixins/base.py
jnt_django_toolbox/admin/mixins/clickable_links.py
jnt_django_toolbox/admin/mixins/generic_foreign_key.py
jnt_django_toolbox/admin/mixins/generic_foreign_key_inline.py
jnt_django_toolbox/admin/mixins/readonly_widgets.py
jnt_django_toolbox/admin/views/__init__.py
jnt_django_toolbox/admin/views/autocomplete.py
jnt_django_toolbox/admin/views/base_admin_page.py
jnt_django_toolbox/admin/views/base_instance_model_admin_page.py
jnt_django_toolbox/admin/views/base_model_admin_page.py
jnt_django_toolbox/apps.py
jnt_django_toolbox/consts/__init__.py
jnt_django_toolbox/consts/time.py
jnt_django_toolbox/context_managers/__init__.py
jnt_django_toolbox/context_managers/global_lock.py
jnt_django_toolbox-0.9.15.dist-info/METADATA
jnt_django_toolbox-0.9.15.dist-info/WHEEL
jnt_django_toolbox-0.9.15.dist-info/RECORD
