Metadata-Version: 2.1
Name: jnt-django-toolbox
Version: 0.9.15
Summary: 
Author: junte
Author-email: tech@junte.ru
Requires-Python: >=3.10,<4.0
Classifier: Environment :: Web Environment
Classifier: Framework :: Django :: 3.2
Classifier: Intended Audience :: Developers
Classifier: License :: OSI Approved :: MIT License
Classifier: Operating System :: OS Independent
Classifier: Programming Language :: Python :: 3
Classifier: Programming Language :: Python :: 3.10
Classifier: Programming Language :: Python :: 3.11
Classifier: Programming Language :: Python :: 3.12
Classifier: Topic :: Software Development :: Libraries :: Python Modules
Provides-Extra: jaeger
Requires-Dist: dateparser
Requires-Dist: django (>=4.1)
Requires-Dist: jaeger-client ; extra == "jaeger"
